softwareai_engine_library/__init__.py
softwareai_engine_library/AgentDestilation/Agent_destilation.py
softwareai_engine_library/AgentDestilation/__init__.py
softwareai_engine_library/AgentDestilation/__pycache__/Agent_destilation.cpython-312.pyc
softwareai_engine_library/AgentDestilation/__pycache__/Agent_destilation.cpython-39.pyc
softwareai_engine_library/AgentDestilation/__pycache__/__init__.cpython-312.pyc
softwareai_engine_library/AgentDestilation/__pycache__/__init__.cpython-39.pyc
softwareai_engine_library/AgentFiles/AgentFiles.py
softwareai_engine_library/AgentFiles/AgentFilesUpdate.py
softwareai_engine_library/AgentFiles/__init__.py
softwareai_engine_library/AgentFiles/__pycache__/AgentFiles.cpython-312.pyc
softwareai_engine_library/AgentFiles/__pycache__/AgentFiles.cpython-39.pyc
softwareai_engine_library/AgentFiles/__pycache__/AgentFilesUpdate.cpython-312.pyc
softwareai_engine_library/AgentFiles/__pycache__/AgentFilesUpdate.cpython-39.pyc
softwareai_engine_library/AgentFiles/__pycache__/__init__.cpython-312.pyc
softwareai_engine_library/AgentFiles/__pycache__/__init__.cpython-39.pyc
softwareai_engine_library/AutenticateAgent/AuthAgent.py
softwareai_engine_library/AutenticateAgent/__init__.py
softwareai_engine_library/AutenticateAgent/__pycache__/AuthAgent.cpython-312.pyc
softwareai_engine_library/AutenticateAgent/__pycache__/AuthAgent.cpython-39.pyc
softwareai_engine_library/AutenticateAgent/__pycache__/__init__.cpython-312.pyc
softwareai_engine_library/AutenticateAgent/__pycache__/__init__.cpython-39.pyc
softwareai_engine_library/Chat/_init_chat_.py
softwareai_engine_library/Chat/auth/autenticar_usuario.py
softwareai_engine_library/Chat/auth/dynamic_rate_limit.py
softwareai_engine_library/Chat/history/fix_all_conversations.py
softwareai_engine_library/Chat/history/get_conversation_history.py
softwareai_engine_library/Chat/history/save_assistant_message.py
softwareai_engine_library/Chat/history/save_conversation_history.py
softwareai_engine_library-1.0.23.dist-info/METADATA
softwareai_engine_library-1.0.23.dist-info/WHEEL
softwareai_engine_library-1.0.23.dist-info/top_level.txt
softwareai_engine_library-1.0.23.dist-info/RECORD
