Metadata-Version: 2.1
Name: softwareai_engine_library
Version: 1.0.23
Summary: O motor da biblioteca é liberado através do pip para a sincronia do motor em múltiplos agentes
Home-page: https://github.com/SoftwareAI-Company/SoftwareAI
Author: ualerson
Author-email: mediacutsstudio@gmail.com
License: Apache-2.0
Classifier: Programming Language :: Python :: 3
Classifier: License :: OSI Approved :: Apache Software License
Classifier: Operating System :: OS Independent
Requires-Python: >=3.7
Requires-Dist: Flask
Requires-Dist: Flask-CORS
Requires-Dist: user-agents
Requires-Dist: waitress
Requires-Dist: requests
Requires-Dist: python-dotenv
Requires-Dist: PyYAML
Requires-Dist: docker
Requires-Dist: discord.py
Requires-Dist: python-telegram-bot
Requires-Dist: setuptools
Requires-Dist: redis
Requires-Dist: eventlet
Requires-Dist: flask
Requires-Dist: flask-cors
Requires-Dist: flask-limiter
Requires-Dist: flask-socketio
Requires-Dist: pytz
Requires-Dist: celery
Requires-Dist: termcolor
Requires-Dist: stripe
Requires-Dist: openai-whisper
Requires-Dist: torch
Requires-Dist: uiautomator2
Requires-Dist: opencv-python-headless
Requires-Dist: numpy
Requires-Dist: srt
Requires-Dist: yt-dlp
Requires-Dist: psutil
Requires-Dist: schedule
Requires-Dist: google-auth
Requires-Dist: google-api-python-client
Requires-Dist: websockets
Requires-Dist: av
Requires-Dist: firebase-admin
Requires-Dist: transformers
Requires-Dist: proglog
Requires-Dist: openai
Requires-Dist: pandas
Requires-Dist: tiktoken
Requires-Dist: PyGithub
Requires-Dist: typing-extensions
Requires-Dist: reportlab
Requires-Dist: obsws-python
Requires-Dist: huggingface-hub
Requires-Dist: opencv-python
Requires-Dist: google-auth-oauthlib
Requires-Dist: google-auth-httplib2
Requires-Dist: pdfkit
Requires-Dist: chardet
Requires-Dist: markdown
Requires-Dist: unidecode
Requires-Dist: pytest
Requires-Dist: matplotlib
Requires-Dist: flask-dance
Requires-Dist: openai-agents
